{"i":{"8hoH1yFM9B":{"id":"8hoH1yFM9B","type":"slide","setup":{"transparentBg":{"selectedKey":false},"bord":{"size":10,"rad":10},"bg":{"selectedKey":"fill","fill":{"opac":1,"rgb":"#00ff00"}}}},"YqgCHloVI":{"id":"YqgCHloVI","type":"interactive","subtype":"interactivePodCast","setup":{"bg":{"selectedKey":"image","fill":{"opac":1,"rgb":"#FFF"},"img":{"filt":{"opac":100,"gray":0,"blur":0,"tint":{"rgb":"#FFF","opac":0}},"pos":{"type":"fit","fit":{"bg":{"color":{"rgb":"#FFF","opac":100}},"vali":"center","hali":"center"},"crop":{"bg":{"color":{"rgb":"#FFF","opac":0}},"poi":{"x":707,"y":1486.5}},"mask":{"shape":1}},"measures":{"size":{"width":1414,"height":2000}},"orig":{"rType":"asset","rSubType":"image","fileName":"Ubicaci贸n (3).png","fileSize":426032,"val":"mc-6dea554aa47b452a636b6b5073f80670.png","aid":"_-SROLyZ16"}}},"audio":{"orig":{"rType":"asset","rSubType":"audio","fileName":"on.mp3","fileSize":17558,"val":"mc-6a83917f5e71d77eec5ecac818369bca.mp3","aid":"61BWTV3ZXy"}}}},"AKbN72xI3":{"id":"AKbN72xI3","type":"interactive","subtype":"interactivePodCast","setup":{"bg":{"selectedKey":"image","fill":{"opac":1,"rgb":"#FFF"},"img":{"filt":{"opac":100,"gray":0,"blur":0,"tint":{"rgb":"#FFF","opac":0}},"pos":{"type":"fit","fit":{"bg":{"color":{"rgb":"#FFF","opac":100}},"vali":"center","hali":"center"},"crop":{"bg":{"color":{"rgb":"#FFF","opac":0}},"poi":{"x":793,"y":790}},"mask":{"shape":1}},"measures":{"size":{"width":1587,"height":2245}},"orig":{"rType":"asset","rSubType":"image","fileName":"lecci贸n 30 (2).png","fileSize":74404,"val":"mc-5e5cb2cb5266c8a93c1ccf514df93edd.png","aid":"LiTerHxiZW"}}},"audio":{"orig":{"rType":"asset","rSubType":"audio","fileName":"because.mp3","fileSize":45216,"val":"mc-a3d361db3f03c758d77485b8e0dc8c87.mp3","aid":"nCOW_UYXUI"}}}},"KkHiNJ9a7":{"id":"KkHiNJ9a7","type":"interactive","subtype":"interactiveRichText","setup":{"frmeTp":{"selectedKey":"noneFrame"},"bg":{"fill":{"opac":0,"rgb":"#FFF"}},"txt":{"val":{"ops":[{"insert":"Wh Questions","attributes":{"bold":true,"color":"var(--TC2)","background":"transparent"}},{"insert":"\n","attributes":{"size":"giant","align":"center"}}]},"rType":"richtext"},"hali":"","vali":"middle"}},"SmM3oRMjU":{"id":"SmM3oRMjU","type":"interactive","subtype":"interactivePodCast","setup":{"bg":{"selectedKey":"image","fill":{"opac":1,"rgb":"#FFF"},"img":{"filt":{"opac":100,"gray":0,"blur":0,"tint":{"rgb":"#FFF","opac":0}},"pos":{"type":"fit","fit":{"bg":{"color":{"rgb":"#FFF","opac":100}},"vali":"center","hali":"center"},"crop":{"bg":{"color":{"rgb":"#FFF","opac":0}},"poi":{"x":793,"y":790}},"mask":{"shape":1}},"measures":{"size":{"width":1587,"height":2245}},"orig":{"rType":"asset","rSubType":"image","fileName":"lecci贸n 30 (1).png","fileSize":53690,"val":"mc-add919f6299b01771432eea17f5a7d0e.png","aid":"qI0E1MRUxd"}}},"audio":{"orig":{"rType":"asset","rSubType":"audio","fileName":"why.mp3","fileSize":25076,"val":"mc-0cc7f68c94505fe92c4ea1704b1d0575.mp3","aid":"GrBfNGZK43"}}}},"GWxKSkOOu":{"id":"GWxKSkOOu","type":"interactive","subtype":"interactivePodCast","setup":{"bg":{"selectedKey":"image","fill":{"opac":1,"rgb":"#FFF"},"img":{"filt":{"opac":100,"gray":0,"blur":0,"tint":{"rgb":"#FFF","opac":0}},"pos":{"type":"fit","fit":{"bg":{"color":{"rgb":"#FFF","opac":100}},"vali":"center","hali":"center"},"crop":{"bg":{"color":{"rgb":"#FFF","opac":0}},"poi":{"x":793,"y":838}},"mask":{"shape":1}},"measures":{"size":{"width":1587,"height":2245}},"orig":{"rType":"asset","rSubType":"image","fileName":"lecci贸n 30.png","fileSize":55387,"val":"mc-dda1ef33335fbbd9b2a8c87a9abada1a.png","aid":"IORHrDGdz"}}},"audio":{"orig":{"rType":"asset","rSubType":"audio","fileName":"what.mp3","fileSize":20766,"val":"mc-2e7711588d1b36fb50b135a62b1b90e7.mp3","aid":"ZOLAVb0wLe"}}}}},"v":"1"}