{"i":{"QrDgTmJfE3":{"id":"QrDgTmJfE3","type":"slide","setup":{"bg":{"selectedKey":"fill","fill":{"opac":1,"rgb":"#ff0000"}},"transparentBg":{"selectedKey":false},"bord":{"size":10,"rad":10}}},"oXko2ZlxA":{"id":"oXko2ZlxA","type":"interactive","subtype":"interactivePodCast","setup":{"bg":{"selectedKey":"image","fill":{"opac":1,"rgb":"#FFF"},"img":{"filt":{"opac":100,"gray":0,"blur":0,"tint":{"rgb":"#FFF","opac":0}},"pos":{"type":"fit","fit":{"bg":{"color":{"rgb":"#FFF","opac":100}},"vali":"center","hali":"center"},"crop":{"bg":{"color":{"rgb":"#FFF","opac":0}},"poi":{"x":793,"y":790}},"mask":{"shape":1}},"measures":{"size":{"width":1587,"height":2245}},"orig":{"rType":"asset","rSubType":"image","fileName":"lecci贸n 34.png","fileSize":39058,"val":"mc-9c529a64b5abfc2698609c4927a2f5a0.png","aid":"VItHFLrs_"}}},"audio":{"orig":{"rType":"asset","rSubType":"audio","fileName":"this.mp3","fileSize":36817,"val":"mc-ec44a324b9a94e36951e283bd5482402.mp3","aid":"JCXWTzETb"}}}},"k0TigaBWi":{"id":"k0TigaBWi","type":"interactive","subtype":"interactivePodCast","setup":{"bg":{"selectedKey":"image","fill":{"opac":1,"rgb":"#FFF"},"img":{"filt":{"opac":100,"gray":0,"blur":0,"tint":{"rgb":"#FFF","opac":0}},"pos":{"type":"fit","fit":{"bg":{"color":{"rgb":"#FFF","opac":100}},"vali":"center","hali":"center"},"crop":{"bg":{"color":{"rgb":"#FFF","opac":0}},"poi":{"x":793,"y":790}},"mask":{"shape":1}},"measures":{"size":{"width":1587,"height":2245}},"orig":{"rType":"asset","rSubType":"image","fileName":"lecci贸n 34 (2).png","fileSize":43980,"val":"mc-a9df9e123b4919c15963fdb0b9f8fa55.png","aid":"f08TV6wKs"}}},"audio":{"orig":{"rType":"asset","rSubType":"audio","fileName":"These.mp3","fileSize":44749,"val":"mc-ecb65683984fd60dfe1f26c0ad8f9c07.mp3","aid":"uiYgUTWnX"}}}},"6HHErUxr4":{"id":"6HHErUxr4","type":"interactive","subtype":"interactivePodCast","setup":{"bg":{"selectedKey":"image","fill":{"opac":1,"rgb":"#FFF"},"img":{"filt":{"opac":100,"gray":0,"blur":0,"tint":{"rgb":"#FFF","opac":0}},"pos":{"type":"fit","fit":{"bg":{"color":{"rgb":"#FFF","opac":100}},"vali":"center","hali":"center"},"crop":{"bg":{"color":{"rgb":"#FFF","opac":0}},"poi":{"x":793,"y":790}},"mask":{"shape":1}},"measures":{"size":{"width":1587,"height":2245}},"orig":{"rType":"asset","rSubType":"image","fileName":"lecci贸n 34 (3).png","fileSize":46848,"val":"mc-c894e22309512f356731a4491c6af314.png","aid":"gjgQl_4lC"}}},"audio":{"orig":{"rType":"asset","rSubType":"audio","fileName":"Those.mp3","fileSize":41800,"val":"mc-441ef9ca8378d9b1e369a85cd23a007a.mp3","aid":"Onak4MVqf"}}}},"ZKEzrPfA3":{"id":"ZKEzrPfA3","type":"interactive","subtype":"interactivePodCast","setup":{"bg":{"selectedKey":"image","fill":{"opac":1,"rgb":"#FFF"},"img":{"filt":{"opac":100,"gray":0,"blur":0,"tint":{"rgb":"#FFF","opac":0}},"pos":{"type":"fit","fit":{"bg":{"color":{"rgb":"#FFF","opac":100}},"vali":"center","hali":"center"},"crop":{"bg":{"color":{"rgb":"#FFF","opac":0}},"poi":{"x":793,"y":790}},"mask":{"shape":1}},"measures":{"size":{"width":1587,"height":2245}},"orig":{"rType":"asset","rSubType":"image","fileName":"lecci贸n 34 (1).png","fileSize":37151,"val":"mc-45fad2865b8c8b6cf0c81b5c2fa0e024.png","aid":"KwdR9PVsU"}}},"audio":{"orig":{"rType":"asset","rSubType":"audio","fileName":"That.mp3","fileSize":33474,"val":"mc-41444d8046664d46cdeb0767fc239c56.mp3","aid":"tR0WQf3-m"}}}},"K21A9Y1eG":{"id":"K21A9Y1eG","type":"interactive","subtype":"interactiveRichText","setup":{"frmeTp":{"selectedKey":"noneFrame"},"bg":{"fill":{"opac":0,"rgb":"#FFF"}},"txt":{"val":{"ops":[{"insert":"Adjectives","attributes":{"bold":true,"color":"#000000","background":"transparent"}},{"insert":"\n","attributes":{"align":"center","size":"giant"}}]},"rType":"richtext"},"hali":"","vali":"middle"}}},"v":"1"}